websocket_tools/__init__.py
websocket_tools/websocket_loop.py
websocket_tools-0.0.15.dist-info/LICENCE
websocket_tools-0.0.15.dist-info/METADATA
websocket_tools-0.0.15.dist-info/WHEEL
websocket_tools-0.0.15.dist-info/top_level.txt
websocket_tools-0.0.15.dist-info/RECORD
