Metadata-Version: 2.1
Name: websocket-tools
Version: 0.0.15
Summary: A simple module to wrap web socket connection code.
Author-email: sir even <sir_even@icloud.com>
Project-URL: Homepage, https://github.com/sirEven/websocket-tools.git
Classifier: Programming Language :: Python :: 3
Classifier: License :: OSI Approved :: MIT License
Classifier: Operating System :: OS Independent
Requires-Python: >=3.7
License-File: LICENCE
